my_ragas_runtime/__init__.py
my_ragas_runtime/pyarmor_runtime.so
superai_ragas/__init__.py
superai_ragas/_analytics.py
superai_ragas/_version.py
superai_ragas/async_utils.py
superai_ragas/evaluation.py
superai_ragas/exceptions.py
superai_ragas/utils.py
superai_ragas/validation.py
superai_ragas/embeddings/__init__.py
superai_ragas/embeddings/base.py
superai_ragas/langchain/__init__.py
superai_ragas/langchain/evalchain.py
superai_ragas/langsmith/__init__.py
superai_ragas/langsmith/evaluator.py
superai_ragas/llama_index/__init__.py
superai_ragas/llama_index/evaluation.py
superai_ragas/llms/__init__.py
superai_ragas/llms/base.py
superai_ragas/llms/langchain.py
superai_ragas/llms/llamaindex.py
superai_ragas/llms/openai.py
superai_ragas/metrics/__init__.py
superai_ragas/metrics/_answer_correctness.py
superai_ragas/metrics/_answer_correctness_superai.py
superai_ragas/metrics/_answer_recall_superai.py
superai_ragas/metrics/_answer_relevance.py
superai_ragas/metrics/_answer_similarity.py
superai_ragas/metrics/_context_precision.py
superai_ragas/metrics/_context_recall.py
superai_ragas/metrics/_context_relevancy.py
superai_ragas/metrics/_faithfulness.py
superai_ragas/metrics/base.py
superai_ragas/metrics/critique.py
superai_ragas/testset/__init__.py
superai_ragas/testset/prompts.py
superai_ragas/testset/testset_generator.py
superai_ragas/testset/utils.py
superai_ragas/trainset/__init__.py
superai_ragas/trainset/prompts.py
superai_ragas/trainset/trainset_generator.py
superai_ragas/trainset/utils.py
superai_ragas-1.2.1.3.dist-info/METADATA
superai_ragas-1.2.1.3.dist-info/WHEEL
superai_ragas-1.2.1.3.dist-info/top_level.txt
superai_ragas-1.2.1.3.dist-info/RECORD
